conditionalconformal/__init__.py
conditionalconformal/condconf.py
conditionalconformal/condconf2.py
conditionalconformal/density_estimation.py
conditionalconformal/experiment_utils.py
conditionalconformal/lp.py
conditionalconformal/qp.py
conditionalconformal/synthetic_data.py
conditionalconformal/temperatureScaling.py
conditionalconformal/utilities.py
conditionalconformal-0.0.5.dist-info/LICENSE
conditionalconformal-0.0.5.dist-info/METADATA
conditionalconformal-0.0.5.dist-info/WHEEL
conditionalconformal-0.0.5.dist-info/top_level.txt
conditionalconformal-0.0.5.dist-info/RECORD
