Metadata-Version: 2.2
Name: conditionalconformal
Version: 0.0.5
Summary: This package enables conformal prediction with conditional guarantees.
Home-page: https://github.com/jjcherian/conditional-conformal
Author: John Cherian
Author-email: John Cherian <jcherian@stanford.edu>, Isaac Gibbs <igibbs@stanford.edu>
Project-URL: Homepage, https://github.com/jjcherian/conditionalconformal
Project-URL: Bug Tracker, https://github.com/jjcherian/conditionalconformal/issues
Classifier: Programming Language :: Python :: 3
Classifier: License :: OSI Approved :: MIT License
Classifier: Operating System :: OS Independent
Requires-Python: >=3.7
License-File: LICENSE
Requires-Dist: numpy
Requires-Dist: scipy
Requires-Dist: cvxpy
Requires-Dist: scikit-learn
Requires-Dist: matplotlib
Requires-Dist: tqdm
Dynamic: author
Dynamic: home-page
